LICENSE
README.md
setup.py
web_ui_helper/__init__.py
web_ui_helper.egg-info/PKG-INFO
web_ui_helper.egg-info/SOURCES.txt
web_ui_helper.egg-info/dependency_links.txt
web_ui_helper.egg-info/requires.txt
web_ui_helper.egg-info/top_level.txt
web_ui_helper/common/__init__.py
web_ui_helper/common/date_extend.py
web_ui_helper/common/dir.py
web_ui_helper/common/http_proxy.py
web_ui_helper/common/log.py
web_ui_helper/common/metaclass.py
web_ui_helper/common/platforms.py
web_ui_helper/common/webdriver.py
web_ui_helper/decorators/__init__.py
web_ui_helper/decorators/airtest_exception.py
web_ui_helper/decorators/selenium_exception.py
web_ui_helper/selenium/__init__.py
web_ui_helper/selenium/frame/__init__.py
web_ui_helper/selenium/frame/browser.py
web_ui_helper/selenium/parse/__init__.py
web_ui_helper/selenium/parse/ctrip_flight.py
web_ui_helper/selenium/ui/__init__.py
web_ui_helper/selenium/ui/frame.py
web_ui_helper/terminal/__init__.py
web_ui_helper/terminal/device.py