Metadata-Version: 2.1
Name: web-ui-helper
Version: 1.0.9
Summary: This is my web ui helper package
Home-page: https://github.com/ckf10000/web-ui-helper
Author: ckf10000
Author-email: ckf10000@sina.com
Classifier: Programming Language :: Python :: 3
Classifier: License :: OSI Approved :: MIT License
Classifier: Operating System :: OS Independent
License-File: LICENSE
Requires-Dist: selenium>=4.20.0
Requires-Dist: pandas>=2.2.2
Requires-Dist: blinker==1.7.0
Requires-Dist: airtest>=1.3.3
Requires-Dist: pocoui>=1.0.94
Requires-Dist: requests>=2.31.0
Requires-Dist: selenium-wire>=5.1.0
Requires-Dist: webdriver-manager>=4.0.1
Requires-Dist: ddddocr>=1.4.11
Requires-Dist: openpyxl>=3.1.2
